dockers/Dockerfile
dockers/Readme.md
dockers/docker-compose.yml
dockers/requirements.txt
dockers/run-python.sh
examples/zipped_runs/selected_runs.zip
iapytoo/__init__.py
iapytoo/_version.py
iapytoo/dataset/__init__.py
iapytoo/dataset/scaling.py
iapytoo/metrics/__init__.py
iapytoo/metrics/collection.py
iapytoo/metrics/distrib.py
iapytoo/metrics/metric.py
iapytoo/metrics/predefined.py
iapytoo/predictions/__init__.py
iapytoo/predictions/feature.py
iapytoo/predictions/plotters.py
iapytoo/predictions/predictors.py
iapytoo/predictions/types.py
iapytoo/train/__init__.py
iapytoo/train/checkpoint.py
iapytoo/train/context.py
iapytoo/train/factories.py
iapytoo/train/inference.py
iapytoo/train/logger.py
iapytoo/train/loss.py
iapytoo/train/mlflow_model.py
iapytoo/train/training.py
iapytoo/train/valuator.py
iapytoo/train/wgan.py
iapytoo/utils/__init__.py
iapytoo/utils/arguments.py
iapytoo/utils/config.py
iapytoo/utils/display.py
iapytoo/utils/iterative_mean.py
iapytoo/utils/model_config.py
iapytoo/utils/singleton.py
iapytoo/utils/time_utils.py
iapytoo/utils/timer.py
iapytoo/utils/cf/config.json
iapytoo/utils/cf/config.yml
iapytoo/utils/cf/config_test.json
iapytoo-0.0.9.dist-info/licenses/LICENSE
mlflow/relocate_mlruns.py
mlflow/zip_selected_runs.py
iapytoo-0.0.9.dist-info/METADATA
iapytoo-0.0.9.dist-info/WHEEL
iapytoo-0.0.9.dist-info/top_level.txt
iapytoo-0.0.9.dist-info/RECORD
