Metadata-Version: 2.4
Name: iapytoo
Version: 0.0.9
Summary: Un toolkit pour vite coder un modèle pytorch d'IA utilisant MLflow
Author-email: Jean-François Lecomte <zwergon@free.fr>
License: Apache-2.0
Requires-Python: >=3.7
License-File: LICENSE
Dynamic: license-file
